README.md
setup.py
frasco_stripe/__init__.py
frasco_stripe.egg-info/PKG-INFO
frasco_stripe.egg-info/SOURCES.txt
frasco_stripe.egg-info/dependency_links.txt
frasco_stripe.egg-info/not-zip-safe
frasco_stripe.egg-info/requires.txt
frasco_stripe.egg-info/top_level.txt