Metadata-Version: 1.0
Name: frasco-stripe
Version: 0.5.4
Summary: Stripe integration for Frasco
Home-page: http://github.com/frascoweb/frasco-stripe
Author: Maxime Bouroumeau-Fuseau
Author-email: maxime.bouroumeau@gmail.com
License: MIT
Platform: any
